{
  "metadata" : {
    "identifier" : "https://www.dtv-ebook.com/khua-tay-vao-may-troi_20887.html",
    "title" : "Khua Tay Vào Mây Trời",
    "subtitle" : "N/A",
    "author" : {
      "name" : "Nhiều tác giả",
      "sortAs" : ""
    },
    "narrator" : "N/A",
    "language" : "vi",
    "description" : "<p>N/A</p>",
    "publisher" : "N/A",
    "subject" : null,
    "modified" : null,
    "published" : "2024-09-20",
    "duration" : 9155,
    "abridged" : false,
    "conformsTo" : null,
    "numberOfPages" : null,
    "readingProgression" : null,
    "belongsTo" : null,
    "presentation" : null,
    "@type" : "http://schema.org/Audiobook",
    "schema:license" : "https://creativecommons.org/publicdomain/zero/1.0/"
  },
  "links" : [ {
    "rel" : "self",
    "href" : "https://raw.githubusercontent.com/duyhv/book_storage_three6/main/EPUB/EPUB_646cb1555073ac630c81557ee9a413ee.json",
    "type" : "application/audiobook+json"
  }, {
    "rel" : "cover",
    "href" : "https://raw.githubusercontent.com/duyhv/book_storage_three6/main/IMAGE/IMAGE_646cb1555073ac630c81557ee9a413ee.jpg",
    "type" : "image/jpeg",
    "height" : 300,
    "width" : 300
  } ],
  "readingOrder" : [ {
    "href" : "https://archive.org/download/646cb1555073ac630c81557ee9a413ee/1-khua-tay-vao-may-troi-01.mp3",
    "type" : "audio/mpeg",
    "bitrate" : 128,
    "duration" : 2683,
    "title" : "KHUA TAY VAO MAY TROI 01",
    "properties" : null,
    "alternate" : null
  }, {
    "href" : "https://archive.org/download/646cb1555073ac630c81557ee9a413ee/2-khua-tay-vao-may-troi-02.mp3",
    "type" : "audio/mpeg",
    "bitrate" : 128,
    "duration" : 2367,
    "title" : "KHUA TAY VAO MAY TROI 02",
    "properties" : null,
    "alternate" : null
  }, {
    "href" : "https://archive.org/download/646cb1555073ac630c81557ee9a413ee/3-khua-tay-vao-may-troi-03.mp3",
    "type" : "audio/mpeg",
    "bitrate" : 128,
    "duration" : 1997,
    "title" : "KHUA TAY VAO MAY TROI 03",
    "properties" : null,
    "alternate" : null
  }, {
    "href" : "https://archive.org/download/646cb1555073ac630c81557ee9a413ee/4-khua-tay-vao-may-troi-04.mp3",
    "type" : "audio/mpeg",
    "bitrate" : 128,
    "duration" : 2108,
    "title" : "KHUA TAY VAO MAY TROI 04",
    "properties" : null,
    "alternate" : null
  } ],
  "toc" : [ {
    "href" : "https://archive.org/download/646cb1555073ac630c81557ee9a413ee/1-khua-tay-vao-may-troi-01.mp3",
    "title" : "KHUA TAY VAO MAY TROI 01",
    "children" : [ ]
  }, {
    "href" : "https://archive.org/download/646cb1555073ac630c81557ee9a413ee/2-khua-tay-vao-may-troi-02.mp3",
    "title" : "KHUA TAY VAO MAY TROI 02",
    "children" : [ ]
  }, {
    "href" : "https://archive.org/download/646cb1555073ac630c81557ee9a413ee/3-khua-tay-vao-may-troi-03.mp3",
    "title" : "KHUA TAY VAO MAY TROI 03",
    "children" : [ ]
  }, {
    "href" : "https://archive.org/download/646cb1555073ac630c81557ee9a413ee/4-khua-tay-vao-may-troi-04.mp3",
    "title" : "KHUA TAY VAO MAY TROI 04",
    "children" : [ ]
  } ],
  "@context" : "https://readium.org/webpub-manifest/context.jsonld"
}