{
  "metadata" : {
    "identifier" : "https://www.nettruyenio.com/truyen-tranh/khom-lung-86309",
    "title" : "Khom Lưng - Chapter 4",
    "subtitle" : null,
    "author" : null,
    "narrator" : null,
    "language" : "vi",
    "description" : null,
    "publisher" : "N/A",
    "subject" : null,
    "modified" : null,
    "published" : "2023-08-06",
    "duration" : 0,
    "abridged" : false,
    "conformsTo" : "https://readium.org/webpub-manifest/profiles/divina",
    "numberOfPages" : 28,
    "readingProgression" : "ttb",
    "belongsTo" : null,
    "presentation" : {
      "fit" : "width",
      "overflow" : "scrolled",
      "continuous" : true
    },
    "@type" : null,
    "schema:license" : null
  },
  "links" : [ {
    "rel" : "self",
    "href" : "https://raw.githubusercontent.com/thuvienonline40/book_storage_collection/main/comic_manifest.json",
    "type" : "application/divina+json"
  } ],
  "readingOrder" : [ {
    "href" : "https://raw.githubusercontent.com/duyhuynh652018/comic_storage6/main/IMAGE/IMAGE_41003d6949b346b77597a00f4981f82f_22279a22c046229445f26715fbaaf599_ede328f5e631a8bfa4898a37e14fdb40.jpg",
    "type" : "image/jpeg",
    "bitrate" : 0,
    "duration" : 0,
    "title" : null,
    "properties" : null,
    "alternate" : [ {
      "href" : "https://i225.ntcdntempv26.com/data/images/86309/1004678/001-2e6de16.jpg?data=net",
      "type" : "image/jpeg",
      "bitrate" : 0,
      "duration" : 0,
      "title" : null,
      "properties" : null,
      "alternate" : null
    } ]
  }, {
    "href" : "https://raw.githubusercontent.com/duyhuynh652018/comic_storage6/main/IMAGE/IMAGE_41003d6949b346b77597a00f4981f82f_22279a22c046229445f26715fbaaf599_14f8924d1b2eafe7df9b1c8e66cc4333.jpg",
    "type" : "image/jpeg",
    "bitrate" : 0,
    "duration" : 0,
    "title" : null,
    "properties" : null,
    "alternate" : [ {
      "href" : "https://i225.ntcdntempv26.com/data/images/86309/1004678/002-06bcaee.jpg?data=net",
      "type" : "image/jpeg",
      "bitrate" : 0,
      "duration" : 0,
      "title" : null,
      "properties" : null,
      "alternate" : null
    } ]
  }, {
    "href" : "https://raw.githubusercontent.com/duyhuynh652018/comic_storage6/main/IMAGE/IMAGE_41003d6949b346b77597a00f4981f82f_22279a22c046229445f26715fbaaf599_c239dfe13a37ed91f885b306e06bcc39.jpg",
    "type" : "image/jpeg",
    "bitrate" : 0,
    "duration" : 0,
    "title" : null,
    "properties" : null,
    "alternate" : [ {
      "href" : "https://i225.ntcdntempv26.com/data/images/86309/1004678/003-1b2d829.jpg?data=net",
      "type" : "image/jpeg",
      "bitrate" : 0,
      "duration" : 0,
      "title" : null,
      "properties" : null,
      "alternate" : null
    } ]
  }, {
    "href" : "https://raw.githubusercontent.com/duyhuynh652018/comic_storage6/main/IMAGE/IMAGE_41003d6949b346b77597a00f4981f82f_22279a22c046229445f26715fbaaf599_e290525fc8531f83ae76175f38ff140c.jpg",
    "type" : "image/jpeg",
    "bitrate" : 0,
    "duration" : 0,
    "title" : null,
    "properties" : null,
    "alternate" : [ {
      "href" : "https://i225.ntcdntempv26.com/data/images/86309/1004678/004-1d40a1e.jpg?data=net",
      "type" : "image/jpeg",
      "bitrate" : 0,
      "duration" : 0,
      "title" : null,
      "properties" : null,
      "alternate" : null
    } ]
  }, {
    "href" : "https://raw.githubusercontent.com/duyhuynh652018/comic_storage6/main/IMAGE/IMAGE_41003d6949b346b77597a00f4981f82f_22279a22c046229445f26715fbaaf599_0cb5e80ca50ba1ff168a02d92f408349.jpg",
    "type" : "image/jpeg",
    "bitrate" : 0,
    "duration" : 0,
    "title" : null,
    "properties" : null,
    "alternate" : [ {
      "href" : "https://i225.ntcdntempv26.com/data/images/86309/1004678/005-c98d261.jpg?data=net",
      "type" : "image/jpeg",
      "bitrate" : 0,
      "duration" : 0,
      "title" : null,
      "properties" : null,
      "alternate" : null
    } ]
  }, {
    "href" : "https://raw.githubusercontent.com/duyhuynh652018/comic_storage6/main/IMAGE/IMAGE_41003d6949b346b77597a00f4981f82f_22279a22c046229445f26715fbaaf599_74cd305a9368bc7668ff39bb2d83be8f.jpg",
    "type" : "image/jpeg",
    "bitrate" : 0,
    "duration" : 0,
    "title" : null,
    "properties" : null,
    "alternate" : [ {
      "href" : "https://i225.ntcdntempv26.com/data/images/86309/1004678/006-b187c0e.jpg?data=net",
      "type" : "image/jpeg",
      "bitrate" : 0,
      "duration" : 0,
      "title" : null,
      "properties" : null,
      "alternate" : null
    } ]
  }, {
    "href" : "https://raw.githubusercontent.com/duyhuynh652018/comic_storage6/main/IMAGE/IMAGE_41003d6949b346b77597a00f4981f82f_22279a22c046229445f26715fbaaf599_e3a6c9ca766bd9ec85085f5543671755.jpg",
    "type" : "image/jpeg",
    "bitrate" : 0,
    "duration" : 0,
    "title" : null,
    "properties" : null,
    "alternate" : [ {
      "href" : "https://i225.ntcdntempv26.com/data/images/86309/1004678/007-cb80c6a.jpg?data=net",
      "type" : "image/jpeg",
      "bitrate" : 0,
      "duration" : 0,
      "title" : null,
      "properties" : null,
      "alternate" : null
    } ]
  }, {
    "href" : "https://raw.githubusercontent.com/duyhuynh652018/comic_storage6/main/IMAGE/IMAGE_41003d6949b346b77597a00f4981f82f_22279a22c046229445f26715fbaaf599_8a23472ba8775abd1a8ffe1aa6f600ca.jpg",
    "type" : "image/jpeg",
    "bitrate" : 0,
    "duration" : 0,
    "title" : null,
    "properties" : null,
    "alternate" : [ {
      "href" : "https://i225.ntcdntempv26.com/data/images/86309/1004678/008-57f21f9.jpg?data=net",
      "type" : "image/jpeg",
      "bitrate" : 0,
      "duration" : 0,
      "title" : null,
      "properties" : null,
      "alternate" : null
    } ]
  }, {
    "href" : "https://raw.githubusercontent.com/duyhuynh652018/comic_storage6/main/IMAGE/IMAGE_41003d6949b346b77597a00f4981f82f_22279a22c046229445f26715fbaaf599_26fef2e5fd3ee65a6a6b8e9f1e4b5d93.jpg",
    "type" : "image/jpeg",
    "bitrate" : 0,
    "duration" : 0,
    "title" : null,
    "properties" : null,
    "alternate" : [ {
      "href" : "https://i225.ntcdntempv26.com/data/images/86309/1004678/009-a78c56c.jpg?data=net",
      "type" : "image/jpeg",
      "bitrate" : 0,
      "duration" : 0,
      "title" : null,
      "properties" : null,
      "alternate" : null
    } ]
  }, {
    "href" : "https://raw.githubusercontent.com/duyhuynh652018/comic_storage6/main/IMAGE/IMAGE_41003d6949b346b77597a00f4981f82f_22279a22c046229445f26715fbaaf599_93bf672f95dd9971a7c58d4407065a30.jpg",
    "type" : "image/jpeg",
    "bitrate" : 0,
    "duration" : 0,
    "title" : null,
    "properties" : null,
    "alternate" : [ {
      "href" : "https://i225.ntcdntempv26.com/data/images/86309/1004678/010-c690101.jpg?data=net",
      "type" : "image/jpeg",
      "bitrate" : 0,
      "duration" : 0,
      "title" : null,
      "properties" : null,
      "alternate" : null
    } ]
  }, {
    "href" : "https://raw.githubusercontent.com/duyhuynh652018/comic_storage6/main/IMAGE/IMAGE_41003d6949b346b77597a00f4981f82f_22279a22c046229445f26715fbaaf599_755bc396038b6e3f1e6078e0b6b462ab.jpg",
    "type" : "image/jpeg",
    "bitrate" : 0,
    "duration" : 0,
    "title" : null,
    "properties" : null,
    "alternate" : [ {
      "href" : "https://i225.ntcdntempv26.com/data/images/86309/1004678/011-4d5801d.jpg?data=net",
      "type" : "image/jpeg",
      "bitrate" : 0,
      "duration" : 0,
      "title" : null,
      "properties" : null,
      "alternate" : null
    } ]
  }, {
    "href" : "https://raw.githubusercontent.com/duyhuynh652018/comic_storage6/main/IMAGE/IMAGE_41003d6949b346b77597a00f4981f82f_22279a22c046229445f26715fbaaf599_be2a5414911062df1d9dc9b4d90253e1.jpg",
    "type" : "image/jpeg",
    "bitrate" : 0,
    "duration" : 0,
    "title" : null,
    "properties" : null,
    "alternate" : [ {
      "href" : "https://i225.ntcdntempv26.com/data/images/86309/1004678/012-834f752.jpg?data=net",
      "type" : "image/jpeg",
      "bitrate" : 0,
      "duration" : 0,
      "title" : null,
      "properties" : null,
      "alternate" : null
    } ]
  }, {
    "href" : "https://raw.githubusercontent.com/duyhuynh652018/comic_storage6/main/IMAGE/IMAGE_41003d6949b346b77597a00f4981f82f_22279a22c046229445f26715fbaaf599_a58dbd3d133f70716aad7bd7368a20af.jpg",
    "type" : "image/jpeg",
    "bitrate" : 0,
    "duration" : 0,
    "title" : null,
    "properties" : null,
    "alternate" : [ {
      "href" : "https://i225.ntcdntempv26.com/data/images/86309/1004678/013-23f88c9.jpg?data=net",
      "type" : "image/jpeg",
      "bitrate" : 0,
      "duration" : 0,
      "title" : null,
      "properties" : null,
      "alternate" : null
    } ]
  }, {
    "href" : "https://raw.githubusercontent.com/duyhuynh652018/comic_storage6/main/IMAGE/IMAGE_41003d6949b346b77597a00f4981f82f_22279a22c046229445f26715fbaaf599_6a17228a088fe87faa9d70f2e0d48beb.jpg",
    "type" : "image/jpeg",
    "bitrate" : 0,
    "duration" : 0,
    "title" : null,
    "properties" : null,
    "alternate" : [ {
      "href" : "https://i225.ntcdntempv26.com/data/images/86309/1004678/014-7c38546.jpg?data=net",
      "type" : "image/jpeg",
      "bitrate" : 0,
      "duration" : 0,
      "title" : null,
      "properties" : null,
      "alternate" : null
    } ]
  }, {
    "href" : "https://raw.githubusercontent.com/duyhuynh652018/comic_storage6/main/IMAGE/IMAGE_41003d6949b346b77597a00f4981f82f_22279a22c046229445f26715fbaaf599_c0fae9e8979394dd0fca3e40cb7abc91.jpg",
    "type" : "image/jpeg",
    "bitrate" : 0,
    "duration" : 0,
    "title" : null,
    "properties" : null,
    "alternate" : [ {
      "href" : "https://i225.ntcdntempv26.com/data/images/86309/1004678/015-fdd1da2.jpg?data=net",
      "type" : "image/jpeg",
      "bitrate" : 0,
      "duration" : 0,
      "title" : null,
      "properties" : null,
      "alternate" : null
    } ]
  }, {
    "href" : "https://raw.githubusercontent.com/duyhuynh652018/comic_storage6/main/IMAGE/IMAGE_41003d6949b346b77597a00f4981f82f_22279a22c046229445f26715fbaaf599_171afa21b7a93e978cbeb40e571220e0.jpg",
    "type" : "image/jpeg",
    "bitrate" : 0,
    "duration" : 0,
    "title" : null,
    "properties" : null,
    "alternate" : [ {
      "href" : "https://i225.ntcdntempv26.com/data/images/86309/1004678/016-6b27b5b.jpg?data=net",
      "type" : "image/jpeg",
      "bitrate" : 0,
      "duration" : 0,
      "title" : null,
      "properties" : null,
      "alternate" : null
    } ]
  }, {
    "href" : "https://raw.githubusercontent.com/duyhuynh652018/comic_storage6/main/IMAGE/IMAGE_41003d6949b346b77597a00f4981f82f_22279a22c046229445f26715fbaaf599_5b3b19b1ffd96245c73afe01d24a5bf3.jpg",
    "type" : "image/jpeg",
    "bitrate" : 0,
    "duration" : 0,
    "title" : null,
    "properties" : null,
    "alternate" : [ {
      "href" : "https://i225.ntcdntempv26.com/data/images/86309/1004678/017-7e1d6ca.jpg?data=net",
      "type" : "image/jpeg",
      "bitrate" : 0,
      "duration" : 0,
      "title" : null,
      "properties" : null,
      "alternate" : null
    } ]
  }, {
    "href" : "https://raw.githubusercontent.com/duyhuynh652018/comic_storage6/main/IMAGE/IMAGE_41003d6949b346b77597a00f4981f82f_22279a22c046229445f26715fbaaf599_b1df4a2b68b03a985f29ecbf2a7f6110.jpg",
    "type" : "image/jpeg",
    "bitrate" : 0,
    "duration" : 0,
    "title" : null,
    "properties" : null,
    "alternate" : [ {
      "href" : "https://i225.ntcdntempv26.com/data/images/86309/1004678/018-6715c72.jpg?data=net",
      "type" : "image/jpeg",
      "bitrate" : 0,
      "duration" : 0,
      "title" : null,
      "properties" : null,
      "alternate" : null
    } ]
  }, {
    "href" : "https://raw.githubusercontent.com/duyhuynh652018/comic_storage6/main/IMAGE/IMAGE_41003d6949b346b77597a00f4981f82f_22279a22c046229445f26715fbaaf599_7eeb0d47bca3ad475f811ee3b5ffc3dd.jpg",
    "type" : "image/jpeg",
    "bitrate" : 0,
    "duration" : 0,
    "title" : null,
    "properties" : null,
    "alternate" : [ {
      "href" : "https://i225.ntcdntempv26.com/data/images/86309/1004678/019-50233b6.jpg?data=net",
      "type" : "image/jpeg",
      "bitrate" : 0,
      "duration" : 0,
      "title" : null,
      "properties" : null,
      "alternate" : null
    } ]
  }, {
    "href" : "https://raw.githubusercontent.com/duyhuynh652018/comic_storage6/main/IMAGE/IMAGE_41003d6949b346b77597a00f4981f82f_22279a22c046229445f26715fbaaf599_9323dc00320251f7b47b53ac13cf227d.jpg",
    "type" : "image/jpeg",
    "bitrate" : 0,
    "duration" : 0,
    "title" : null,
    "properties" : null,
    "alternate" : [ {
      "href" : "https://i225.ntcdntempv26.com/data/images/86309/1004678/020-c4d3d5c.jpg?data=net",
      "type" : "image/jpeg",
      "bitrate" : 0,
      "duration" : 0,
      "title" : null,
      "properties" : null,
      "alternate" : null
    } ]
  }, {
    "href" : "https://raw.githubusercontent.com/duyhuynh652018/comic_storage6/main/IMAGE/IMAGE_41003d6949b346b77597a00f4981f82f_22279a22c046229445f26715fbaaf599_d5e6b5389599917790327bae3a7b3957.jpg",
    "type" : "image/jpeg",
    "bitrate" : 0,
    "duration" : 0,
    "title" : null,
    "properties" : null,
    "alternate" : [ {
      "href" : "https://i225.ntcdntempv26.com/data/images/86309/1004678/021-5cc79d4.jpg?data=net",
      "type" : "image/jpeg",
      "bitrate" : 0,
      "duration" : 0,
      "title" : null,
      "properties" : null,
      "alternate" : null
    } ]
  }, {
    "href" : "https://raw.githubusercontent.com/duyhuynh652018/comic_storage6/main/IMAGE/IMAGE_41003d6949b346b77597a00f4981f82f_22279a22c046229445f26715fbaaf599_8724aa1f0666148b94dd858e6e1b2dbc.jpg",
    "type" : "image/jpeg",
    "bitrate" : 0,
    "duration" : 0,
    "title" : null,
    "properties" : null,
    "alternate" : [ {
      "href" : "https://i225.ntcdntempv26.com/data/images/86309/1004678/022-4a4d4ef.jpg?data=net",
      "type" : "image/jpeg",
      "bitrate" : 0,
      "duration" : 0,
      "title" : null,
      "properties" : null,
      "alternate" : null
    } ]
  }, {
    "href" : "https://raw.githubusercontent.com/duyhuynh652018/comic_storage6/main/IMAGE/IMAGE_41003d6949b346b77597a00f4981f82f_22279a22c046229445f26715fbaaf599_264fe538309950d7056c0f7a23cfb31a.jpg",
    "type" : "image/jpeg",
    "bitrate" : 0,
    "duration" : 0,
    "title" : null,
    "properties" : null,
    "alternate" : [ {
      "href" : "https://i225.ntcdntempv26.com/data/images/86309/1004678/023-39c2ae1.jpg?data=net",
      "type" : "image/jpeg",
      "bitrate" : 0,
      "duration" : 0,
      "title" : null,
      "properties" : null,
      "alternate" : null
    } ]
  }, {
    "href" : "https://raw.githubusercontent.com/duyhuynh652018/comic_storage6/main/IMAGE/IMAGE_41003d6949b346b77597a00f4981f82f_22279a22c046229445f26715fbaaf599_f340bed7f9572cba82d65c043ab1bff2.jpg",
    "type" : "image/jpeg",
    "bitrate" : 0,
    "duration" : 0,
    "title" : null,
    "properties" : null,
    "alternate" : [ {
      "href" : "https://i225.ntcdntempv26.com/data/images/86309/1004678/024-4d76896.jpg?data=net",
      "type" : "image/jpeg",
      "bitrate" : 0,
      "duration" : 0,
      "title" : null,
      "properties" : null,
      "alternate" : null
    } ]
  }, {
    "href" : "https://raw.githubusercontent.com/duyhuynh652018/comic_storage6/main/IMAGE/IMAGE_41003d6949b346b77597a00f4981f82f_22279a22c046229445f26715fbaaf599_d41fca059a976724450609455a865586.jpg",
    "type" : "image/jpeg",
    "bitrate" : 0,
    "duration" : 0,
    "title" : null,
    "properties" : null,
    "alternate" : [ {
      "href" : "https://i225.ntcdntempv26.com/data/images/86309/1004678/025-be0b934.jpg?data=net",
      "type" : "image/jpeg",
      "bitrate" : 0,
      "duration" : 0,
      "title" : null,
      "properties" : null,
      "alternate" : null
    } ]
  } ],
  "toc" : null,
  "@context" : "https://readium.org/webpub-manifest/context.jsonld"
}